embedded_jubatus.cpython-36m-x86_64-linux-gnu.so
embedded_jubatus-1.1.1.post2.dist-info/WHEEL
embedded_jubatus-1.1.1.post2.dist-info/RECORD
embedded_jubatus-1.1.1.post2.dist-info/METADATA
embedded_jubatus-1.1.1.post2.dist-info/top_level.txt
.libsembedded_jubatus/libjubatus_util_math-ccd348d2.so.1.1.1
.libsembedded_jubatus/libjubatus_util_data-075def10.so.1.1.1
.libsembedded_jubatus/libjubatus_util_lang-472d1020.so.1.1.1
.libsembedded_jubatus/libjubatus_util-a9841fc8.so.1.1.1
.libsembedded_jubatus/libmsgpack-6079424c.so.3.0.0
.libsembedded_jubatus/libjubatus_util_system-01806a6a.so.1.1.1
.libsembedded_jubatus/libjubatus_util_text-663a040d.so.1.1.1
.libsembedded_jubatus/libjubatus_util_concurrent-04029af5.so.1.1.1
.libsembedded_jubatus/libonig-c76702e1.so.2.0.0
.libsembedded_jubatus/libjubatus_core-7bec9d9e.so.1.1.1
