Metadata-Version: 1.1
Name: embedded_jubatus
Version: 1.1.1.post2
Summary: embedded-jubatus-python is a Python bridge to call Jubatus Core library.
Home-page: http://jubat.us
Author: PFN & NTT
Author-email: jubatus-team@googlegroups.com
License: LGPLv2
Download-URL: http://pypi.python.org/pypi/embedded_jubatus
Platform: UNKNOWN
Classifier: Intended Audience :: Developers
Classifier: Intended Audience :: Science/Research
Classifier: Topic :: Scientific/Engineering :: Information Analysis
Classifier: License :: OSI Approved :: GNU Lesser General Public License v2 (LGPLv2)
Classifier: Programming Language :: Python
Classifier: Programming Language :: Python :: 2
Classifier: Programming Language :: Python :: 3
